pathlibfs/__init__.py
pathlibfs/exception.py
pathlibfs/path.py
pathlibfs/s3_support.py
pathlibfs-0.5.0.dist-info/LICENSE
pathlibfs-0.5.0.dist-info/METADATA
pathlibfs-0.5.0.dist-info/WHEEL
pathlibfs-0.5.0.dist-info/RECORD
