Metadata-Version: 2.1
Name: pathlibfs
Version: 0.5.0
Summary: pathlib 🤝 fsspec, manipulate remote filesystem paths.
License: MIT
Author: Hiroyuki "Roy" Tanaka
Author-email: aflc0x@gmail.com
Requires-Python: >=3.8,<4.0
Classifier: License :: OSI Approved :: MIT License
Classifier: Programming Language :: Python :: 3
Classifier: Programming Language :: Python :: 3.8
Classifier: Programming Language :: Python :: 3.9
Classifier: Programming Language :: Python :: 3.10
Classifier: Programming Language :: Python :: 3.11
Requires-Dist: fsspec (>=2023.5.0)
